auto_ddns-0.0.7.dist-info/METADATA
auto_ddns-0.0.7.dist-info/WHEEL
auto_ddns-0.0.7.dist-info/entry_points.txt
auto_ddns-0.0.7.dist-info/licenses/LICENSE
auto_ddns/__init__.py
auto_ddns/__main__.py
auto_ddns/__version__.py
auto_ddns/getter/__init__.py
auto_ddns/getter/base.py
auto_ddns/getter/public.py
auto_ddns/getter/snmp.py
auto_ddns/model/__init__.py
auto_ddns/model/config.py
auto_ddns/model/record.py
auto_ddns/setter/__init__.py
auto_ddns/setter/base.py
auto_ddns/setter/dnspod.py
auto_ddns/utils.py
auto_ddns-0.0.7.dist-info/RECORD
