Metadata-Version: 2.1
Name: auto-ddns
Version: 0.0.7
Summary: auto config dns
Author-Email: Zhan Rongrui <2742392377@qq.com>
License: MIT
Requires-Python: >=3.10
Requires-Dist: tencentcloud-sdk-python-dnspod
Requires-Dist: loguru>=0.7.2
Requires-Dist: rich>=13.7.0
Requires-Dist: pyparsing>=3.1.1
Requires-Dist: typer[all]>=0.9.0
Requires-Dist: cachetools>=5.3.2
Requires-Dist: pydantic>=2.5.3
Requires-Dist: auto-token>=0.0.4
Requires-Dist: PyYaml>=6.0.1
Requires-Dist: toml>=0.10.2
Requires-Dist: httpx>=0.26.0
Requires-Dist: watchfiles; extra == "watch"
Requires-Dist: auto-ddns[watch]; extra == "all"
Provides-Extra: watch
Provides-Extra: all
